MANIFEST.in
README.rst
setup.py
dragonfluid/__init__.py
dragonfluid/_decorators.py
dragonfluid/_elements.py
dragonfluid/_grammars.py
dragonfluid/_rules.py
dragonfluid/_specparsers.py
dragonfluid/_support.py
dragonfluid.egg-info/PKG-INFO
dragonfluid.egg-info/SOURCES.txt
dragonfluid.egg-info/dependency_links.txt
dragonfluid.egg-info/requires.txt
dragonfluid.egg-info/top_level.txt