Metadata-Version: 1.1
Name: dragonfluid
Version: 0.9.0a5
Summary: A dragonfly extension to allow voice commands to be spoken together without pausing. Supports Dragon NaturallySpeaking and Windows Speech Recognition.
Home-page: https://github.com/chajadan/dragonfluid
Author: Charles J. Daniels
Author-email: dragonfluid@chajadan.net
License: http://www.chajadan.net/licenses/NFFFLicenseV1.txt
Keywords: speech recognition,voice coding,dragonfly,Dragon,Dragon NaturallySpeaking,Windows Speech Recognition,WSR
Platform: UNKNOWN
Classifier: Development Status :: 3 - Alpha
Classifier: Intended Audience :: Developers
Classifier: License :: Public Domain
Classifier: Programming Language :: Python :: 2 :: Only
Classifier: Programming Language :: Python :: 2.7
Classifier: Topic :: Adaptive Technologies
Classifier: Topic :: Software Development :: Libraries :: Python Modules
Classifier: Topic :: Software Development :: User Interfaces
Classifier: Topic :: Other/Nonlisted Topic
